<?xml version="1.0" encoding="UTF-8"?>
<DEFECTS>
  <DEFECT>
    <SFA>
      <FILEPATH>e:\personalwork\townyfrowny\townyfrowny\townyfrowny\</FILEPATH>
      <FILENAME>fastnoise.h</FILENAME>
      <LINE>48</LINE>
      <COLUMN>1</COLUMN>
    </SFA>
    <DEFECTCODE>26495</DEFECTCODE>
    <DESCRIPTION>Variable 'FastNoise::m_perm' is uninitialized. Always initialize a member variable (type.6).</DESCRIPTION>
    <FUNCTION>FastNoise::{ctor}</FUNCTION>
    <DECORATED>??0FastNoise@@QAE@H@Z</DECORATED>
    <FUNCLINE>48</FUNCLINE>
    <PATH></PATH>
  </DEFECT>
  <DEFECT>
    <SFA>
      <FILEPATH>e:\personalwork\townyfrowny\townyfrowny\townyfrowny\</FILEPATH>
      <FILENAME>fastnoise.h</FILENAME>
      <LINE>48</LINE>
      <COLUMN>1</COLUMN>
    </SFA>
    <DEFECTCODE>26495</DEFECTCODE>
    <DESCRIPTION>Variable 'FastNoise::m_perm12' is uninitialized. Always initialize a member variable (type.6).</DESCRIPTION>
    <FUNCTION>FastNoise::{ctor}</FUNCTION>
    <DECORATED>??0FastNoise@@QAE@H@Z</DECORATED>
    <FUNCLINE>48</FUNCLINE>
    <PATH></PATH>
  </DEFECT>
  <DEFECT>
    <SFA>
      <FILEPATH>e:\personalwork\townyfrowny\townyfrowny\townyfrowny\</FILEPATH>
      <FILENAME>fastnoise.h</FILENAME>
      <LINE>48</LINE>
      <COLUMN>1</COLUMN>
    </SFA>
    <DEFECTCODE>26495</DEFECTCODE>
    <DESCRIPTION>Variable 'FastNoise::m_fractalBounding' is uninitialized. Always initialize a member variable (type.6).</DESCRIPTION>
    <FUNCTION>FastNoise::{ctor}</FUNCTION>
    <DECORATED>??0FastNoise@@QAE@H@Z</DECORATED>
    <FUNCLINE>48</FUNCLINE>
    <PATH></PATH>
  </DEFECT>
  <DEFECT>
    <SFA>
      <FILEPATH>e:\personalwork\townyfrowny\townyfrowny\townyfrowny\</FILEPATH>
      <FILENAME>worldtile.h</FILENAME>
      <LINE>6</LINE>
      <COLUMN>1</COLUMN>
    </SFA>
    <DEFECTCODE>26495</DEFECTCODE>
    <DESCRIPTION>Variable 'WorldTile::tileEntitiesCount' is uninitialized. Always initialize a member variable (type.6).</DESCRIPTION>
    <FUNCTION>WorldTile::{ctor}</FUNCTION>
    <DECORATED>??0WorldTile@@QAE@PAVFastNoise@@AAVWorld@@FF@Z</DECORATED>
    <FUNCLINE>6</FUNCLINE>
    <PATH></PATH>
  </DEFECT>
  <DEFECT>
    <SFA>
      <FILEPATH>e:\personalwork\townyfrowny\townyfrowny\townyfrowny\</FILEPATH>
      <FILENAME>worldtile.h</FILENAME>
      <LINE>6</LINE>
      <COLUMN>1</COLUMN>
    </SFA>
    <DEFECTCODE>26495</DEFECTCODE>
    <DESCRIPTION>Variable 'WorldTile::contentsVolume' is uninitialized. Always initialize a member variable (type.6).</DESCRIPTION>
    <FUNCTION>WorldTile::{ctor}</FUNCTION>
    <DECORATED>??0WorldTile@@QAE@PAVFastNoise@@AAVWorld@@FF@Z</DECORATED>
    <FUNCLINE>6</FUNCLINE>
    <PATH></PATH>
  </DEFECT>
  <DEFECT>
    <SFA>
      <FILEPATH>e:\personalwork\townyfrowny\townyfrowny\townyfrowny\</FILEPATH>
      <FILENAME>worldtile.h</FILENAME>
      <LINE>6</LINE>
      <COLUMN>1</COLUMN>
    </SFA>
    <DEFECTCODE>26495</DEFECTCODE>
    <DESCRIPTION>Variable 'WorldTile::hcost' is uninitialized. Always initialize a member variable (type.6).</DESCRIPTION>
    <FUNCTION>WorldTile::{ctor}</FUNCTION>
    <DECORATED>??0WorldTile@@QAE@PAVFastNoise@@AAVWorld@@FF@Z</DECORATED>
    <FUNCLINE>6</FUNCLINE>
    <PATH></PATH>
  </DEFECT>
  <DEFECT>
    <SFA>
      <FILEPATH>e:\personalwork\townyfrowny\townyfrowny\townyfrowny\</FILEPATH>
      <FILENAME>worldtile.h</FILENAME>
      <LINE>6</LINE>
      <COLUMN>1</COLUMN>
    </SFA>
    <DEFECTCODE>26495</DEFECTCODE>
    <DESCRIPTION>Variable 'WorldTile::gcost' is uninitialized. Always initialize a member variable (type.6).</DESCRIPTION>
    <FUNCTION>WorldTile::{ctor}</FUNCTION>
    <DECORATED>??0WorldTile@@QAE@PAVFastNoise@@AAVWorld@@FF@Z</DECORATED>
    <FUNCLINE>6</FUNCLINE>
    <PATH></PATH>
  </DEFECT>
  <DEFECT>
    <SFA>
      <FILEPATH>e:\personalwork\townyfrowny\townyfrowny\townyfrowny\</FILEPATH>
      <FILENAME>worldtile.h</FILENAME>
      <LINE>6</LINE>
      <COLUMN>1</COLUMN>
    </SFA>
    <DEFECTCODE>26495</DEFECTCODE>
    <DESCRIPTION>Variable 'WorldTile::pathingParent' is uninitialized. Always initialize a member variable (type.6).</DESCRIPTION>
    <FUNCTION>WorldTile::{ctor}</FUNCTION>
    <DECORATED>??0WorldTile@@QAE@PAVFastNoise@@AAVWorld@@FF@Z</DECORATED>
    <FUNCLINE>6</FUNCLINE>
    <PATH></PATH>
  </DEFECT>
  <DEFECT>
    <SFA>
      <FILEPATH>e:\personalwork\townyfrowny\townyfrowny\townyfrowny\</FILEPATH>
      <FILENAME>rapidcsv.h</FILENAME>
      <LINE>403</LINE>
      <COLUMN>2</COLUMN>
    </SFA>
    <DEFECTCODE>26495</DEFECTCODE>
    <DESCRIPTION>Variable 'rapidcsv::Document::mConverterParams' is uninitialized. Always initialize a member variable (type.6).</DESCRIPTION>
    <FUNCTION>rapidcsv::Document::{ctor}</FUNCTION>
    <DECORATED>??0Document@rapidcsv@@QAE@ABV01@@Z</DECORATED>
    <FUNCLINE>403</FUNCLINE>
    <PATH></PATH>
  </DEFECT>
  <DEFECT>
    <SFA>
      <FILEPATH>e:\personalwork\townyfrowny\townyfrowny\townyfrowny\</FILEPATH>
      <FILENAME>rapidcsv.h</FILENAME>
      <LINE>403</LINE>
      <COLUMN>2</COLUMN>
    </SFA>
    <DEFECTCODE>26495</DEFECTCODE>
    <DESCRIPTION>Variable 'rapidcsv::Document::mLabelParams' is uninitialized. Always initialize a member variable (type.6).</DESCRIPTION>
    <FUNCTION>rapidcsv::Document::{ctor}</FUNCTION>
    <DECORATED>??0Document@rapidcsv@@QAE@ABV01@@Z</DECORATED>
    <FUNCLINE>403</FUNCLINE>
    <PATH></PATH>
  </DEFECT>
  <DEFECT>
    <SFA>
      <FILEPATH>e:\personalwork\townyfrowny\townyfrowny\townyfrowny\</FILEPATH>
      <FILENAME>rapidcsv.h</FILENAME>
      <LINE>403</LINE>
      <COLUMN>2</COLUMN>
    </SFA>
    <DEFECTCODE>26495</DEFECTCODE>
    <DESCRIPTION>Variable 'rapidcsv::Document::mSeparatorParams' is uninitialized. Always initialize a member variable (type.6).</DESCRIPTION>
    <FUNCTION>rapidcsv::Document::{ctor}</FUNCTION>
    <DECORATED>??0Document@rapidcsv@@QAE@ABV01@@Z</DECORATED>
    <FUNCLINE>403</FUNCLINE>
    <PATH></PATH>
  </DEFECT>
  <DEFECT>
    <SFA>
      <FILEPATH>e:\personalwork\townyfrowny\townyfrowny\townyfrowny\</FILEPATH>
      <FILENAME>entity_living.h</FILENAME>
      <LINE>51</LINE>
      <COLUMN>1</COLUMN>
    </SFA>
    <DEFECTCODE>26495</DEFECTCODE>
    <DESCRIPTION>Variable 'Entity_Living::decompositionLvl' is uninitialized. Always initialize a member variable (type.6).</DESCRIPTION>
    <FUNCTION>Entity_Living::{ctor}</FUNCTION>
    <DECORATED>??0Entity_Living@@QAE@_WPAVTaskManager@@PAVWorld@@V?$vector@W4TargetedHumanBehaviors@Entity@@V?$allocator@W4TargetedHumanBehaviors@Entity@@@std@@@std@@@Z</DECORATED>
    <FUNCLINE>51</FUNCLINE>
    <PATH></PATH>
  </DEFECT>
  <DEFECT>
    <SFA>
      <FILEPATH>e:\personalwork\townyfrowny\townyfrowny\townyfrowny\</FILEPATH>
      <FILENAME>inputhandler.h</FILENAME>
      <LINE>22</LINE>
      <COLUMN>1</COLUMN>
    </SFA>
    <DEFECTCODE>26495</DEFECTCODE>
    <DESCRIPTION>Variable 'InputHandler::pilotingPlayer' is uninitialized. Always initialize a member variable (type.6).</DESCRIPTION>
    <FUNCTION>InputHandler::{ctor}</FUNCTION>
    <DECORATED>??0InputHandler@@QAE@PAVPathFinder@@PAVWorld@@PAVRenderWindow@sf@@@Z</DECORATED>
    <FUNCLINE>22</FUNCLINE>
    <PATH></PATH>
  </DEFECT>
  <DEFECT>
    <SFA>
      <FILEPATH>e:\personalwork\townyfrowny\townyfrowny\townyfrowny\</FILEPATH>
      <FILENAME>inputhandler.h</FILENAME>
      <LINE>22</LINE>
      <COLUMN>1</COLUMN>
    </SFA>
    <DEFECTCODE>26495</DEFECTCODE>
    <DESCRIPTION>Variable 'InputHandler::movementThreshold' is uninitialized. Always initialize a member variable (type.6).</DESCRIPTION>
    <FUNCTION>InputHandler::{ctor}</FUNCTION>
    <DECORATED>??0InputHandler@@QAE@PAVPathFinder@@PAVWorld@@PAVRenderWindow@sf@@@Z</DECORATED>
    <FUNCLINE>22</FUNCLINE>
    <PATH></PATH>
  </DEFECT>
  <DEFECT>
    <SFA>
      <FILEPATH>e:\personalwork\townyfrowny\townyfrowny\townyfrowny\</FILEPATH>
      <FILENAME>entityhandler.h</FILENAME>
      <LINE>24</LINE>
      <COLUMN>1</COLUMN>
    </SFA>
    <DEFECTCODE>26495</DEFECTCODE>
    <DESCRIPTION>Variable 'EntityHandler::taskManager' is uninitialized. Always initialize a member variable (type.6).</DESCRIPTION>
    <FUNCTION>EntityHandler::{ctor}</FUNCTION>
    <DECORATED>??0EntityHandler@@QAE@XZ</DECORATED>
    <FUNCLINE>24</FUNCLINE>
    <PATH></PATH>
  </DEFECT>
  <DEFECT>
    <SFA>
      <FILEPATH>e:\personalwork\townyfrowny\townyfrowny\townyfrowny\</FILEPATH>
      <FILENAME>entityhandler.h</FILENAME>
      <LINE>24</LINE>
      <COLUMN>1</COLUMN>
    </SFA>
    <DEFECTCODE>26495</DEFECTCODE>
    <DESCRIPTION>Variable 'EntityHandler::handler' is uninitialized. Always initialize a member variable (type.6).</DESCRIPTION>
    <FUNCTION>EntityHandler::{ctor}</FUNCTION>
    <DECORATED>??0EntityHandler@@QAE@XZ</DECORATED>
    <FUNCLINE>24</FUNCLINE>
    <PATH></PATH>
  </DEFECT>
  <DEFECT>
    <SFA>
      <FILEPATH>e:\personalwork\townyfrowny\townyfrowny\townyfrowny\</FILEPATH>
      <FILENAME>task.h</FILENAME>
      <LINE>10</LINE>
      <COLUMN>1</COLUMN>
    </SFA>
    <DEFECTCODE>26495</DEFECTCODE>
    <DESCRIPTION>Variable 'Task::finished' is uninitialized. Always initialize a member variable (type.6).</DESCRIPTION>
    <FUNCTION>Task::{ctor}</FUNCTION>
    <DECORATED>??0Task@@QAE@HH@Z</DECORATED>
    <FUNCLINE>10</FUNCLINE>
    <PATH></PATH>
  </DEFECT>
  <DEFECT>
    <SFA>
      <FILEPATH>e:\personalwork\townyfrowny\townyfrowny\townyfrowny\</FILEPATH>
      <FILENAME>task.h</FILENAME>
      <LINE>10</LINE>
      <COLUMN>1</COLUMN>
    </SFA>
    <DEFECTCODE>26495</DEFECTCODE>
    <DESCRIPTION>Variable 'Task::began' is uninitialized. Always initialize a member variable (type.6).</DESCRIPTION>
    <FUNCTION>Task::{ctor}</FUNCTION>
    <DECORATED>??0Task@@QAE@HH@Z</DECORATED>
    <FUNCLINE>10</FUNCLINE>
    <PATH></PATH>
  </DEFECT>
  <DEFECT>
    <SFA>
      <FILEPATH>e:\personalwork\townyfrowny\townyfrowny\townyfrowny\</FILEPATH>
      <FILENAME>task.h</FILENAME>
      <LINE>10</LINE>
      <COLUMN>1</COLUMN>
    </SFA>
    <DEFECTCODE>26495</DEFECTCODE>
    <DESCRIPTION>Variable 'Task::world' is uninitialized. Always initialize a member variable (type.6).</DESCRIPTION>
    <FUNCTION>Task::{ctor}</FUNCTION>
    <DECORATED>??0Task@@QAE@HH@Z</DECORATED>
    <FUNCLINE>10</FUNCLINE>
    <PATH></PATH>
  </DEFECT>
  <DEFECT>
    <SFA>
      <FILEPATH>e:\personalwork\townyfrowny\townyfrowny\townyfrowny\</FILEPATH>
      <FILENAME>task.h</FILENAME>
      <LINE>10</LINE>
      <COLUMN>1</COLUMN>
    </SFA>
    <DEFECTCODE>26495</DEFECTCODE>
    <DESCRIPTION>Variable 'Task::issuer' is uninitialized. Always initialize a member variable (type.6).</DESCRIPTION>
    <FUNCTION>Task::{ctor}</FUNCTION>
    <DECORATED>??0Task@@QAE@HH@Z</DECORATED>
    <FUNCLINE>10</FUNCLINE>
    <PATH></PATH>
  </DEFECT>
  <DEFECT>
    <SFA>
      <FILEPATH>e:\personalwork\townyfrowny\townyfrowny\townyfrowny\</FILEPATH>
      <FILENAME>task.h</FILENAME>
      <LINE>10</LINE>
      <COLUMN>1</COLUMN>
    </SFA>
    <DEFECTCODE>26495</DEFECTCODE>
    <DESCRIPTION>Variable 'Task::tickCount' is uninitialized. Always initialize a member variable (type.6).</DESCRIPTION>
    <FUNCTION>Task::{ctor}</FUNCTION>
    <DECORATED>??0Task@@QAE@HH@Z</DECORATED>
    <FUNCLINE>10</FUNCLINE>
    <PATH></PATH>
  </DEFECT>
  <DEFECT>
    <SFA>
      <FILEPATH>e:\personalwork\townyfrowny\townyfrowny\townyfrowny\</FILEPATH>
      <FILENAME>task.h</FILENAME>
      <LINE>10</LINE>
      <COLUMN>1</COLUMN>
    </SFA>
    <DEFECTCODE>26495</DEFECTCODE>
    <DESCRIPTION>Variable 'Task::ticks' is uninitialized. Always initialize a member variable (type.6).</DESCRIPTION>
    <FUNCTION>Task::{ctor}</FUNCTION>
    <DECORATED>??0Task@@QAE@HH@Z</DECORATED>
    <FUNCLINE>10</FUNCLINE>
    <PATH></PATH>
  </DEFECT>
  <DEFECT>
    <SFA>
      <FILEPATH>e:\personalwork\townyfrowny\townyfrowny\townyfrowny\</FILEPATH>
      <FILENAME>task.h</FILENAME>
      <LINE>10</LINE>
      <COLUMN>1</COLUMN>
    </SFA>
    <DEFECTCODE>26495</DEFECTCODE>
    <DESCRIPTION>Variable 'Task::ownerEntity' is uninitialized. Always initialize a member variable (type.6).</DESCRIPTION>
    <FUNCTION>Task::{ctor}</FUNCTION>
    <DECORATED>??0Task@@QAE@HH@Z</DECORATED>
    <FUNCLINE>10</FUNCLINE>
    <PATH></PATH>
  </DEFECT>
  <DEFECT>
    <SFA>
      <FILEPATH>e:\personalwork\townyfrowny\townyfrowny\townyfrowny\</FILEPATH>
      <FILENAME>task.h</FILENAME>
      <LINE>57</LINE>
      <COLUMN>1</COLUMN>
    </SFA>
    <DEFECTCODE>26495</DEFECTCODE>
    <DESCRIPTION>Variable 'Task_EntityRetrieval::sprialIndex' is uninitialized. Always initialize a member variable (type.6).</DESCRIPTION>
    <FUNCTION>Task_EntityRetrieval::{ctor}</FUNCTION>
    <DECORATED>??0Task_EntityRetrieval@@QAE@H_NHH@Z</DECORATED>
    <FUNCLINE>57</FUNCLINE>
    <PATH></PATH>
  </DEFECT>
  <DEFECT>
    <SFA>
      <FILEPATH>e:\personalwork\townyfrowny\townyfrowny\townyfrowny\</FILEPATH>
      <FILENAME>task.h</FILENAME>
      <LINE>57</LINE>
      <COLUMN>1</COLUMN>
    </SFA>
    <DEFECTCODE>26495</DEFECTCODE>
    <DESCRIPTION>Variable 'Task_EntityRetrieval::onlyLiving' is uninitialized. Always initialize a member variable (type.6).</DESCRIPTION>
    <FUNCTION>Task_EntityRetrieval::{ctor}</FUNCTION>
    <DECORATED>??0Task_EntityRetrieval@@QAE@H_NHH@Z</DECORATED>
    <FUNCLINE>57</FUNCLINE>
    <PATH></PATH>
  </DEFECT>
  <DEFECT>
    <SFA>
      <FILEPATH>e:\personalwork\townyfrowny\townyfrowny\townyfrowny\</FILEPATH>
      <FILENAME>task.h</FILENAME>
      <LINE>57</LINE>
      <COLUMN>1</COLUMN>
    </SFA>
    <DEFECTCODE>26495</DEFECTCODE>
    <DESCRIPTION>Variable 'Task_EntityRetrieval::spiralTicks' is uninitialized. Always initialize a member variable (type.6).</DESCRIPTION>
    <FUNCTION>Task_EntityRetrieval::{ctor}</FUNCTION>
    <DECORATED>??0Task_EntityRetrieval@@QAE@H_NHH@Z</DECORATED>
    <FUNCLINE>57</FUNCLINE>
    <PATH></PATH>
  </DEFECT>
  <DEFECT>
    <SFA>
      <FILEPATH>e:\personalwork\townyfrowny\townyfrowny\townyfrowny\</FILEPATH>
      <FILENAME>task.h</FILENAME>
      <LINE>59</LINE>
      <COLUMN>46</COLUMN>
    </SFA>
    <DEFECTCODE>26451</DEFECTCODE>
    <DESCRIPTION>Arithmetic overflow: Using operator '+' on a 4 byte value and then casting the result to a 8 byte value. Cast the value to the wider type before calling operator '+' to avoid overflow (io.2).</DESCRIPTION>
    <FUNCTION>Task_EntityRetrieval::{ctor}</FUNCTION>
    <DECORATED>??0Task_EntityRetrieval@@QAE@H_NHH@Z</DECORATED>
    <FUNCLINE>57</FUNCLINE>
    <PATH></PATH>
  </DEFECT>
  <DEFECT>
    <SFA>
      <FILEPATH>e:\personalwork\townyfrowny\townyfrowny\townyfrowny\</FILEPATH>
      <FILENAME>task.h</FILENAME>
      <LINE>59</LINE>
      <COLUMN>41</COLUMN>
    </SFA>
    <DEFECTCODE>26451</DEFECTCODE>
    <DESCRIPTION>Arithmetic overflow: Using operator '*' on a 4 byte value and then casting the result to a 8 byte value. Cast the value to the wider type before calling operator '*' to avoid overflow (io.2).</DESCRIPTION>
    <FUNCTION>Task_EntityRetrieval::{ctor}</FUNCTION>
    <DECORATED>??0Task_EntityRetrieval@@QAE@H_NHH@Z</DECORATED>
    <FUNCLINE>57</FUNCLINE>
    <PATH></PATH>
  </DEFECT>
  <DEFECT>
    <SFA>
      <FILEPATH>e:\personalwork\townyfrowny\townyfrowny\townyfrowny\</FILEPATH>
      <FILENAME>task.h</FILENAME>
      <LINE>63</LINE>
      <COLUMN>1</COLUMN>
    </SFA>
    <DEFECTCODE>26495</DEFECTCODE>
    <DESCRIPTION>Variable 'Task_EntityRetrieval::sprialIndex' is uninitialized. Always initialize a member variable (type.6).</DESCRIPTION>
    <FUNCTION>Task_EntityRetrieval::{ctor}</FUNCTION>
    <DECORATED>??0Task_EntityRetrieval@@QAE@H_N0V?$vector@HV?$allocator@H@std@@@std@@HH@Z</DECORATED>
    <FUNCLINE>63</FUNCLINE>
    <PATH></PATH>
  </DEFECT>
  <DEFECT>
    <SFA>
      <FILEPATH>e:\personalwork\townyfrowny\townyfrowny\townyfrowny\</FILEPATH>
      <FILENAME>task.h</FILENAME>
      <LINE>63</LINE>
      <COLUMN>1</COLUMN>
    </SFA>
    <DEFECTCODE>26495</DEFECTCODE>
    <DESCRIPTION>Variable 'Task_EntityRetrieval::spiralTicks' is uninitialized. Always initialize a member variable (type.6).</DESCRIPTION>
    <FUNCTION>Task_EntityRetrieval::{ctor}</FUNCTION>
    <DECORATED>??0Task_EntityRetrieval@@QAE@H_N0V?$vector@HV?$allocator@H@std@@@std@@HH@Z</DECORATED>
    <FUNCLINE>63</FUNCLINE>
    <PATH></PATH>
  </DEFECT>
  <DEFECT>
    <SFA>
      <FILEPATH>e:\personalwork\townyfrowny\townyfrowny\townyfrowny\</FILEPATH>
      <FILENAME>task.h</FILENAME>
      <LINE>66</LINE>
      <COLUMN>46</COLUMN>
    </SFA>
    <DEFECTCODE>26451</DEFECTCODE>
    <DESCRIPTION>Arithmetic overflow: Using operator '+' on a 4 byte value and then casting the result to a 8 byte value. Cast the value to the wider type before calling operator '+' to avoid overflow (io.2).</DESCRIPTION>
    <FUNCTION>Task_EntityRetrieval::{ctor}</FUNCTION>
    <DECORATED>??0Task_EntityRetrieval@@QAE@H_N0V?$vector@HV?$allocator@H@std@@@std@@HH@Z</DECORATED>
    <FUNCLINE>63</FUNCLINE>
    <PATH></PATH>
  </DEFECT>
  <DEFECT>
    <SFA>
      <FILEPATH>e:\personalwork\townyfrowny\townyfrowny\townyfrowny\</FILEPATH>
      <FILENAME>task.h</FILENAME>
      <LINE>66</LINE>
      <COLUMN>41</COLUMN>
    </SFA>
    <DEFECTCODE>26451</DEFECTCODE>
    <DESCRIPTION>Arithmetic overflow: Using operator '*' on a 4 byte value and then casting the result to a 8 byte value. Cast the value to the wider type before calling operator '*' to avoid overflow (io.2).</DESCRIPTION>
    <FUNCTION>Task_EntityRetrieval::{ctor}</FUNCTION>
    <DECORATED>??0Task_EntityRetrieval@@QAE@H_N0V?$vector@HV?$allocator@H@std@@@std@@HH@Z</DECORATED>
    <FUNCLINE>63</FUNCLINE>
    <PATH></PATH>
  </DEFECT>
  <DEFECT>
    <SFA>
      <FILEPATH>e:\personalwork\townyfrowny\townyfrowny\townyfrowny\</FILEPATH>
      <FILENAME>task.h</FILENAME>
      <LINE>123</LINE>
      <COLUMN>1</COLUMN>
    </SFA>
    <DEFECTCODE>26495</DEFECTCODE>
    <DESCRIPTION>Variable 'Task_Search_Singluar::FoundTargetEntity' is uninitialized. Always initialize a member variable (type.6).</DESCRIPTION>
    <FUNCTION>Task_Search_Singluar::{ctor}</FUNCTION>
    <DECORATED>??0Task_Search_Singluar@@QAE@H_N0V?$vector@HV?$allocator@H@std@@@std@@HH@Z</DECORATED>
    <FUNCLINE>123</FUNCLINE>
    <PATH></PATH>
  </DEFECT>
  <DEFECT>
    <SFA>
      <FILEPATH>e:\personalwork\townyfrowny\townyfrowny\townyfrowny\</FILEPATH>
      <FILENAME>task.h</FILENAME>
      <LINE>123</LINE>
      <COLUMN>1</COLUMN>
    </SFA>
    <DEFECTCODE>26495</DEFECTCODE>
    <DESCRIPTION>Variable 'Task_Search_Singluar::FoundTarget' is uninitialized. Always initialize a member variable (type.6).</DESCRIPTION>
    <FUNCTION>Task_Search_Singluar::{ctor}</FUNCTION>
    <DECORATED>??0Task_Search_Singluar@@QAE@H_N0V?$vector@HV?$allocator@H@std@@@std@@HH@Z</DECORATED>
    <FUNCLINE>123</FUNCLINE>
    <PATH></PATH>
  </DEFECT>
  <DEFECT>
    <SFA>
      <FILEPATH>e:\personalwork\townyfrowny\townyfrowny\townyfrowny\</FILEPATH>
      <FILENAME>task.h</FILENAME>
      <LINE>154</LINE>
      <COLUMN>1</COLUMN>
    </SFA>
    <DEFECTCODE>26495</DEFECTCODE>
    <DESCRIPTION>Variable 'Task_SelectRandomEntityFromList::selected' is uninitialized. Always initialize a member variable (type.6).</DESCRIPTION>
    <FUNCTION>Task_SelectRandomEntityFromList::{ctor}</FUNCTION>
    <DECORATED>??0Task_SelectRandomEntityFromList@@QAE@PAV?$vector@PAUEntity@@V?$allocator@PAUEntity@@@std@@@std@@HH@Z</DECORATED>
    <FUNCLINE>154</FUNCLINE>
    <PATH></PATH>
  </DEFECT>
  <DEFECT>
    <SFA>
      <FILEPATH>e:\personalwork\townyfrowny\townyfrowny\townyfrowny\</FILEPATH>
      <FILENAME>task.h</FILENAME>
      <LINE>154</LINE>
      <COLUMN>1</COLUMN>
    </SFA>
    <DEFECTCODE>26495</DEFECTCODE>
    <DESCRIPTION>Variable 'Task_SelectRandomEntityFromList::selectedTarget' is uninitialized. Always initialize a member variable (type.6).</DESCRIPTION>
    <FUNCTION>Task_SelectRandomEntityFromList::{ctor}</FUNCTION>
    <DECORATED>??0Task_SelectRandomEntityFromList@@QAE@PAV?$vector@PAUEntity@@V?$allocator@PAUEntity@@@std@@@std@@HH@Z</DECORATED>
    <FUNCLINE>154</FUNCLINE>
    <PATH></PATH>
  </DEFECT>
  <DEFECT>
    <SFA>
      <FILEPATH>e:\personalwork\townyfrowny\townyfrowny\townyfrowny\</FILEPATH>
      <FILENAME>task.h</FILENAME>
      <LINE>169</LINE>
      <COLUMN>1</COLUMN>
    </SFA>
    <DEFECTCODE>26495</DEFECTCODE>
    <DESCRIPTION>Variable 'Task_WalkTo::pathfinder' is uninitialized. Always initialize a member variable (type.6).</DESCRIPTION>
    <FUNCTION>Task_WalkTo::{ctor}</FUNCTION>
    <DECORATED>??0Task_WalkTo@@QAE@PAVPathFinder@@HPAPAUEntity@@HH@Z</DECORATED>
    <FUNCLINE>169</FUNCLINE>
    <PATH></PATH>
  </DEFECT>
  <DEFECT>
    <SFA>
      <FILEPATH>e:\personalwork\townyfrowny\townyfrowny\townyfrowny\</FILEPATH>
      <FILENAME>task.h</FILENAME>
      <LINE>169</LINE>
      <COLUMN>1</COLUMN>
    </SFA>
    <DEFECTCODE>26495</DEFECTCODE>
    <DESCRIPTION>Variable 'Task_WalkTo::target' is uninitialized. Always initialize a member variable (type.6).</DESCRIPTION>
    <FUNCTION>Task_WalkTo::{ctor}</FUNCTION>
    <DECORATED>??0Task_WalkTo@@QAE@PAVPathFinder@@HPAPAUEntity@@HH@Z</DECORATED>
    <FUNCLINE>169</FUNCLINE>
    <PATH></PATH>
  </DEFECT>
  <DEFECT>
    <SFA>
      <FILEPATH>e:\personalwork\townyfrowny\townyfrowny\townyfrowny\</FILEPATH>
      <FILENAME>task.h</FILENAME>
      <LINE>174</LINE>
      <COLUMN>1</COLUMN>
    </SFA>
    <DEFECTCODE>26495</DEFECTCODE>
    <DESCRIPTION>Variable 'Task_WalkTo::targetEntity' is uninitialized. Always initialize a member variable (type.6).</DESCRIPTION>
    <FUNCTION>Task_WalkTo::{ctor}</FUNCTION>
    <DECORATED>??0Task_WalkTo@@QAE@PAVPathFinder@@HPAPAV?$Vector2@H@sf@@HH@Z</DECORATED>
    <FUNCLINE>174</FUNCLINE>
    <PATH></PATH>
  </DEFECT>
  <DEFECT>
    <SFA>
      <FILEPATH>e:\personalwork\townyfrowny\townyfrowny\townyfrowny\</FILEPATH>
      <FILENAME>task.h</FILENAME>
      <LINE>174</LINE>
      <COLUMN>1</COLUMN>
    </SFA>
    <DEFECTCODE>26495</DEFECTCODE>
    <DESCRIPTION>Variable 'Task_WalkTo::pathfinder' is uninitialized. Always initialize a member variable (type.6).</DESCRIPTION>
    <FUNCTION>Task_WalkTo::{ctor}</FUNCTION>
    <DECORATED>??0Task_WalkTo@@QAE@PAVPathFinder@@HPAPAV?$Vector2@H@sf@@HH@Z</DECORATED>
    <FUNCLINE>174</FUNCLINE>
    <PATH></PATH>
  </DEFECT>
  <DEFECT>
    <SFA>
      <FILEPATH>e:\personalwork\townyfrowny\townyfrowny\townyfrowny\</FILEPATH>
      <FILENAME>task.h</FILENAME>
      <LINE>208</LINE>
      <COLUMN>1</COLUMN>
    </SFA>
    <DEFECTCODE>26495</DEFECTCODE>
    <DESCRIPTION>Variable 'Task_PickUp::entity' is uninitialized. Always initialize a member variable (type.6).</DESCRIPTION>
    <FUNCTION>Task_PickUp::{ctor}</FUNCTION>
    <DECORATED>??0Task_PickUp@@QAE@V?$vector@HV?$allocator@H@std@@@std@@HH@Z</DECORATED>
    <FUNCLINE>208</FUNCLINE>
    <PATH></PATH>
  </DEFECT>
  <DEFECT>
    <SFA>
      <FILEPATH>e:\personalwork\townyfrowny\townyfrowny\townyfrowny\</FILEPATH>
      <FILENAME>task.h</FILENAME>
      <LINE>322</LINE>
      <COLUMN>1</COLUMN>
    </SFA>
    <DEFECTCODE>26495</DEFECTCODE>
    <DESCRIPTION>Variable 'Task_LocateStockDesignation::FoundTarget' is uninitialized. Always initialize a member variable (type.6).</DESCRIPTION>
    <FUNCTION>Task_LocateStockDesignation::{ctor}</FUNCTION>
    <DECORATED>??0Task_LocateStockDesignation@@QAE@H_NW4Type@Designation@@PAPAUEntity@@HH@Z</DECORATED>
    <FUNCLINE>322</FUNCLINE>
    <PATH></PATH>
  </DEFECT>
</DEFECTS>